LICENSE
MANIFEST.in
README.rst
VERSION
setup.py
linker/__init__.py
linker/linker.py
linker.egg-info/PKG-INFO
linker.egg-info/SOURCES.txt
linker.egg-info/dependency_links.txt
linker.egg-info/top_level.txt