Metadata-Version: 1.1
Name: linker
Version: 0.1.0
Summary: link files based on name
Home-page: https://github.com/charlesthomas/linker
Author: Charles Thomas
Author-email: ch@rlesthom.as
License: The MIT License (MIT)
